hausalang/__init__.py
hausalang/core/__init__.py
hausalang/core/errors.py
hausalang/core/executor.py
hausalang/core/formatters.py
hausalang/core/interpreter.py
hausalang/core/interpreter_debug.py
hausalang/core/lexer.py
hausalang/core/parser.py
hausalang/core/perser.py
hausalang/repl/__init__.py
hausalang/repl/__main__.py
hausalang/repl/directives.py
hausalang/repl/input_handler.py
hausalang/repl/session.py
hausalang-1.1.0.dist-info/METADATA
hausalang-1.1.0.dist-info/WHEEL
hausalang-1.1.0.dist-info/top_level.txt
hausalang-1.1.0.dist-info/RECORD
