Metadata-Version: 2.4
Name: hausalang
Version: 1.1.0
Summary: Hausalang: A Hausa-based educational programming language with structured error reporting
Author-email: Hausalang Development Team <dev@hausalang.org>
License: MIT
Project-URL: Homepage, https://github.com/mnura361234-ship-it/hausalang
Project-URL: Documentation, https://github.com/mnura361234-ship-it/hausalang/blob/main/README.md
Project-URL: Repository, https://github.com/mnura361234-ship-it/hausalang.git
Project-URL: Issues, https://github.com/mnura361234-ship-it/hausalang/issues
Keywords: hausa,language,interpreter,educational,error-handling
Classifier: Development Status :: 4 - Beta
Classifier: Intended Audience :: Education
Classifier: License :: OSI Approved :: MIT License
Classifier: Operating System :: OS Independent
Classifier: Programming Language :: Python
Classifier: Programming Language :: Python :: 3
Classifier: Programming Language :: Python :: 3.9
Classifier: Programming Language :: Python :: 3.10
Classifier: Programming Language :: Python :: 3.11
Classifier: Programming Language :: Python :: 3.12
Classifier: Programming Language :: Python :: 3.13
Classifier: Topic :: Education
Classifier: Topic :: Software Development :: Interpreters
Requires-Python: >=3.9
Provides-Extra: dev
Requires-Dist: black>=24.1.0; extra == "dev"
Requires-Dist: ruff>=0.4.4; extra == "dev"
Requires-Dist: mypy>=1.7.0; extra == "dev"
Requires-Dist: pytest>=9.0.0; extra == "dev"
Requires-Dist: pytest-cov>=4.1.0; extra == "dev"
Requires-Dist: coverage[toml]>=7.4.0; extra == "dev"
Requires-Dist: pre-commit>=3.5.0; extra == "dev"
Requires-Dist: bandit>=1.7.5; extra == "dev"
